paper_search_mcp/__init__.py
paper_search_mcp/paper.py
paper_search_mcp/server.py
paper_search_mcp/academic_platforms/__init__.py
paper_search_mcp/academic_platforms/arxiv.py
paper_search_mcp/academic_platforms/biorxiv.py
paper_search_mcp/academic_platforms/crossref.py
paper_search_mcp/academic_platforms/google_scholar.py
paper_search_mcp/academic_platforms/hub.py
paper_search_mcp/academic_platforms/iacr.py
paper_search_mcp/academic_platforms/medrxiv.py
paper_search_mcp/academic_platforms/pubmed.py
paper_search_mcp/academic_platforms/sci_hub.py
paper_search_mcp/academic_platforms/semantic.py
iflow_mcp_paper_search_mcp-0.1.3.dist-info/METADATA
iflow_mcp_paper_search_mcp-0.1.3.dist-info/WHEEL
iflow_mcp_paper_search_mcp-0.1.3.dist-info/entry_points.txt
iflow_mcp_paper_search_mcp-0.1.3.dist-info/licenses/LICENSE
iflow_mcp_paper_search_mcp-0.1.3.dist-info/RECORD
